make/__init__.py
make/__main__.py
make/errors.py
make/template.py
make/make_get/__init__.py
make/make_get/make_get.py
make/make_project/__init__.py
make/make_project/make_project.py
make/make_project/data_medium/__init__.py
make/make_project/data_medium/base.py
make/make_project/data_medium/dry_run.py
make/make_project/data_medium/local.py
make/make_project/data_medium/zipsource.py
make/make_project/parsers/__init__.py
make/make_project/parsers/cookiecutter_parser.py
make/make_project/parsers/ini_parser.py
make/make_project/parsers/json_parser.py
make-0.1.6.dist-info/METADATA
make-0.1.6.dist-info/WHEEL
make-0.1.6.dist-info/top_level.txt
make-0.1.6.dist-info/RECORD
