Metadata-Version: 2.1
Name: make
Version: 0.1.6
Summary: Create project layout from jinja2 templates.
Home-page: https://github.com/fholmer/make
Author: Frode Holmer
Author-email: fholmer+make@gmail.com
License: BSD License
Project-URL: Source Code, https://github.com/fholmer/make
Keywords: make project template
Platform: UNKNOWN
Classifier: Development Status :: 5 - Production/Stable
Classifier: Environment :: Console
Classifier: Intended Audience :: Developers
Classifier: License :: OSI Approved :: BSD License
Classifier: Programming Language :: Python :: 3
Classifier: Programming Language :: Python :: 3.5
Classifier: Programming Language :: Python :: 3.6
Classifier: Programming Language :: Python :: 3.7
Classifier: Programming Language :: Python :: 3.8
Classifier: Operating System :: POSIX :: Linux
Classifier: Operating System :: Microsoft :: Windows
Requires-Dist: Jinja2
Requires-Dist: jinja2-time
